[{"title":"Visualize Your Graph with RNeo4j and visNetwork","url":"nicolewhite.github.io\/2015\/06\/18\/visualize-your-graph-with-rneo4j-and-visNetwork.html"},{"title":"Understanding the Impact of Cassandra Compact Storage","url":"blog.librato.com\/posts\/cassandra-compact-storage"},{"title":"Accumulo: Application Development, Table Design, and Best Practices","url":"www.amazon.com\/gp\/product\/1449374182\/ref=as_li_tl"},{"title":"Mongoop","url":"github.com\/Lujeni\/mongoop"},{"title":"cassandra-lucene-index","url":"github.com\/Stratio\/cassandra-lucene-index"},{"title":"CouchPillow","url":"rubygems.org\/gems\/couchpillow"},{"title":"Mango","url":"github.com\/cloudant\/mango"},{"title":"MongoDB 3.0.5","url":"blog.mongodb.org\/post\/125287953143\/mongodb-305-is-released"},{"title":"Webinar: 3 Ways MongoDB is Driving the FinTech Revolution","url":"www.mongodb.com\/webinar\/3-ways-mongodb-is-driving-the-fintech-revolution"},{"title":"Webinar: Strongly Typed Languages and Flexible Schemas","url":"www.mongodb.com\/webinar\/strongly-typed-languages-and-flexible-schemas"},{"title":"SecurityScorecard JVM Redis Usage - New York, NY","url":"www.meetup.com\/New-York-REDIS-Meetup\/events\/224071157\/"},{"title":"Visualizing your Neo4j Data with Tom Sawyer Perspectives - San Francisco, CA","url":"www.meetup.com\/graphdb-sf\/events\/224220613\/"},{"title":"Optimizing Redis Usage For Caching","url":"sorentwo.com\/2015\/07\/27\/optimizing-redis-usage-for-caching.html"},{"title":"IBM Acquires Compose, Inc. to Expand Cloud Data Services","url":"developer.ibm.com\/bluemix\/2015\/07\/23\/welcome-compose\/"},{"title":"Building A Group Messaging App with Meteor, MongoDB and Twilio","url":"www.twilio.com\/blog\/2015\/07\/building-a-group-messaging-app-with-meteor-mongodb-and-twilio.html"},{"title":"MongoDB on AWS","url":"d0.awsstatic.com\/whitepapers\/AWS_NoSQL_MongoDB.pdf"},{"title":"Using Couchbase in Your Ionic Framework Application Part 2","url":"blog.couchbase.com\/using-couchbase-in-your-ionic-framework-application-part-2"},{"title":"Hive Transaction Feature in Hive 1.0","url":"www.mapr.com\/blog\/hive-transaction-feature-hive-10"},{"title":"Speeding up Existing Apps with a Redis Cache","url":"www.sitepoint.com\/speeding-up-existing-apps-with-a-redis-cache"},{"title":"Your Ultimate Guide to Rolling Upgrades","url":"www.mongodb.com\/blog\/post\/your-ultimate-guide-to-rolling-upgrades"},{"title":"Thrift Client Authentication Support in Apache HBase 1.0","url":"blog.cloudera.com\/blog\/2015\/07\/thrift-client-authentication-support-in-apache-hbase-1-0\/"},{"title":"Full Stack Engineer at Namely (New York, NY)","url":"jobs.lever.co\/namely\/b3b9894e-8eb0-4596-8c4f-7a93b7154467"},{"title":"even in Rails","url":"nandovieira.com\/using-postgresql-and-jsonb-with-ruby-on-rails"},{"title":"Read\u00a0this\u00a0on\u00a0the\u00a0Web","url":"postgresweekly.com\/issues\/117"},{"title":"Analyzing Extreme Distributions in PostgreSQL","url":"tech.zalando.com\/blog\/analyzing-extreme-distributions-in-postgresql\/"},{"title":"Live Postgres Training with Free Certification","url":"www.enterprisedb.com\/store\/products\/dba-training\/01t500000031mz3AAA"},{"title":"Announcing pg_shard 1.2","url":"www.citusdata.com\/blog\/21-jason\/185-announcing-pg-shard-1-2"},{"title":"About the PGConf Silicon Valley PostgreSQL Conference","url":"www.pgconfsv.com\/"},{"title":"Presenting JSONB Data As A Traditional Relation for Hibernate and JPAs","url":"www.enterprisedb.com\/postgres-plus-edb-blog\/jamey-hanson\/presenting-jsonb-data-traditional-relation-hibernate-and-jpas"},{"title":"Why NoSQL Mattered, and SQL Still Matters","url":"medium.com\/s-c-a-l-e\/database-guru-on-why-nosql-matters-and-sql-still-matters-c64239fe84fd"},{"title":"7 Common Database Design Errors","url":"www.vertabelo.com\/blog\/technical-articles\/7-common-database-design-errors"},{"title":"Work with the 2.984618%","url":"www.launchbit.com\/taz\/11159-6010-111"},{"title":"Amazon Aurora Now Available","url":"aws.amazon.com\/blogs\/aws\/now-available-amazon-aurora\/"},{"title":"mycli: A Better Command Line Interface for MySQL and MariaDB","url":"mycli.net\/"},{"title":"Documenting Your PostgreSQL Database","url":"www.craigkerstiens.com\/2013\/07\/29\/documenting-your-postgres-database\/"},{"title":"Building Analytics at 500px","url":"medium.com\/@samson_hu\/building-analytics-at-500px-92e9a7005c83"},{"title":"Database Design: Email Confirmation and Recovering Passwords","url":"www.vertabelo.com\/blog\/technical-articles\/database-design-email-confirmation-and-recovering-passwords"},{"title":"SQL Server Indexing Strategies: Clustered, NonClustered, and Filtered Indexes","url":"www.vertabelo.com\/blog\/technical-articles\/sql-server-indexing-strategies-clustered-nonclustered-and-filtered-indexes"},{"title":"Using Set Theory to Integrate Development and Deployment","url":"www.databasejournal.com\/sqletc\/using-set-theory-to-integrate-development-and-deployment.html"},{"title":"App Analytics Workbook","url":"www.launchbit.com\/taz\/11185-5708-111"},{"title":"Mongob: Collection-Based Backup Tool for MongoDB","url":"github.com\/cmpitg\/mongob"},{"title":"SQLsmith: A Tool That Generates Random SQL Queries","url":"github.com\/anse1\/sqlsmith"},{"title":"Read\u00a0this\u00a0on\u00a0the\u00a0Web","url":"postgresweekly.com\/issues\/116"},{"title":"Transaction ID Wraparound in Postgres","url":"blog.getsentry.com\/2015\/07\/23\/transaction-id-wraparound-in-postgres.html"},{"title":"PGStrom: Postgres Extension That Offloads Work to GPU Devices","url":"wiki.postgresql.org\/wiki\/PGStrom"},{"title":"Real-Time Integration of PostgreSQL and Kafka","url":"www.confluent.io\/blog\/bottled-water-real-time-integration-of-postgresql-and-kafka\/"},{"title":"Building Your Own User Analytics System In SQL","url":"www.periscope.io\/blog\/how-to-build-your-own-user-analytics-in-sql.html"},{"title":"Unsafe UPSERT using WITH Clauses","url":"www.databasesoup.com\/2015\/07\/unsafe-upsert-using-with-clauses.html"},{"title":"PipelineDB: Streaming Postgres","url":"www.databasesoup.com\/2015\/07\/pipelinedb-streaming-postgres.html"},{"title":"pgMemento: Versioning and Transaction Management for Postgres","url":"github.com\/pgMemento\/pgMemento"},{"title":"Database Engineer, Brentwood, TN (onsite, full time)","url":"www.daveramsey.com\/careers\/opportunities"}]