[{"title":"limonade","url":"https:\/\/github.com\/sofadesign\/limonade","source":"github.com"},{"title":"tonic","url":"https:\/\/github.com\/peej\/tonic","source":"github.com"},{"title":"prophecy","url":"https:\/\/github.com\/phpspec\/prophecy","source":"github.com"},{"title":"geotools","url":"https:\/\/github.com\/thephpleague\/geotools","source":"github.com"},{"title":"cilex","url":"https:\/\/github.com\/Cilex\/Cilex","source":"github.com"},{"title":"phan","url":"https:\/\/github.com\/rlerdorf\/phan","source":"github.com"},{"title":"iniscan","url":"https:\/\/github.com\/psecio\/iniscan\/tree\/master","source":"github.com"},{"title":"cloak","url":"https:\/\/github.com\/holyshared\/cloak\/tree\/master","source":"github.com"},{"title":"stream-php","url":"https:\/\/github.com\/tbarbugli\/stream-php\/tree\/master","source":"github.com"},{"title":"phalcon","url":"https:\/\/github.com\/phalcon\/incubator","source":"github.com"},{"title":"agent","url":"https:\/\/github.com\/jenssegers\/agent","source":"github.com"},{"title":"The Power of Three","url":"http:\/\/launchbit.com\/taz\/10754-6018-*|EMAIL_UID|*","source":"launchbit.com"},{"title":"Acquia Podcast -\u00a0How and Why We Use Drupal - A Business Owner's Perspective","url":"https:\/\/www.acquia.com\/podcast\/resources\/podcasts\/how-and-why-we-use-drupal-business-owners-perspective\/29\/10\/2015\/3289571","source":"acquia.com"},{"title":"MageTalk Magento Podcast #68 - The King of The Wiki","url":"http:\/\/magetalk.com\/magetalk-episode-68-the-king-of-the-wiki\/","source":"magetalk.com"},{"title":"What Makes Phpstorm Great for PHP Development","url":"https:\/\/nomadphp.com\/2015\/10\/29\/what-makes-phpstorm-great-for-php-development\/","source":"nomadphp.com"},{"title":"How to Parse XML With SimpleXML and PHP","url":"http:\/\/www.johnmorrisonline.com\/how-to-parse-xml-with-simplexml-and-php\/","source":"johnmorrisonline.com"},{"title":"Interviewing Christian Wenz, talking about PHP, .NET & Las Vegas","url":"http:\/\/blog.feryn.eu\/2015\/10\/26\/interviewing-christian-wenz-talking-about-php-net-las-vegas\/","source":"feryn.eu"},{"title":"php[architect] November 2015 issue released","url":"https:\/\/www.phparch.com\/magazine\/2015-2\/november\/","source":"phparch.com"},{"title":"bootstrapcms","url":"https:\/\/github.com\/BootstrapCMS\/CMS","source":"github.com"},{"title":"flight","url":"https:\/\/github.com\/mikecao\/flight","source":"github.com"},{"title":"pimple","url":"https:\/\/github.com\/silexphp\/Pimple","source":"github.com"},{"title":"fastroute","url":"https:\/\/github.com\/nikic\/FastRoute","source":"github.com"},{"title":"stringy","url":"https:\/\/github.com\/danielstjules\/Stringy","source":"github.com"},{"title":"PHP 5.6.15 is available","url":"http:\/\/php.net\/index.php#id2015-10-29-2","source":"php.net"},{"title":"PHP 7.0.0 RC 6 Released","url":"http:\/\/php.net\/archive\/2015.php#id2015-10-29-1","source":"php.net"},{"title":"Drupal 8.0.0 will be released on November 19, 2015","url":"https:\/\/www.drupal.org\/node\/2605142","source":"drupal.org"},{"title":"dev\/hell Podcast Episode 67 - Working For The Weekend","url":"http:\/\/devhell.info\/post\/2015-10-27\/working-for-the-weekend\/","source":"devhell.info"},{"title":"Voices of the ElePHPant - Interview with Chase Peeler","url":"https:\/\/voicesoftheelephpant.com\/2015\/10\/23\/interview-with-chase-peeler\/","source":"voicesoftheelephpant.com"},{"title":"Laravel IO Podcast:\u00a0Episode 37 - I Love The Things You Are Saying","url":"http:\/\/www.laravelpodcast.com\/episodes\/19454-episode-37-i-love-the-things-you-are-saying","source":"laravelpodcast.com"},{"title":"Three Devs and a Maybe Podcast -\u00a0Let's TalkTalk about Security","url":"http:\/\/threedevsandamaybe.com\/lets-talktalk-about-security\/","source":"threedevsandamaybe.com"},{"title":"That Podcast Episode 24:\u00a0The Last One... With a Friends Themed Title\r\n Because Dave gets frustrated trying to think them up.","url":"https:\/\/thatpodcast.io\/episodes\/episode-24-the-last-one-with-a-friends-themed-title","source":"thatpodcast.io"},{"title":"PHP Benelux Conference - January 29-30th 2016, Antwerp","url":"https:\/\/cfp.phpbenelux.eu\/","source":"phpbenelux.eu"},{"title":"PHP Design Patterns","url":"http:\/\/www.phpbuilder.com\/articles\/application-architecture\/design\/php-design-patterns.html","source":"phpbuilder.com"},{"title":"Changing Author Homepage URL Properly in WordPress","url":"http:\/\/hasin.me\/2015\/10\/31\/changing-author-homepage-url-properly-in-wordpress\/","source":"hasin.me"},{"title":"Running LDAP Tests on travis-ci","url":"http:\/\/cweiske.de\/tagebuch\/ldap-server-travis.htm","source":"cweiske.de"},{"title":"Running Zend Server on Google Cloud Platform","url":"http:\/\/blog.zend.com\/2015\/10\/20\/running-zend-server-on-google-cloud-platform\/#.Vjj-Z7fhDIU","source":"zend.com"},{"title":"Laravel 5.2 - A Look at What\u2019s Coming","url":"https:\/\/laravel-news.com\/2015\/11\/laravel-5-2-a-look-at-whats-coming\/","source":"laravel-news.com"},{"title":"First Look at Flarum \u2013 Next Generation Forums Made Simple","url":"http:\/\/www.sitepoint.com\/first-look-at-flarum-next-generation-forums-made-simple\/","source":"sitepoint.com"},{"title":"PHP 7 Nested Anonymous Classes Tutorial","url":"http:\/\/www.phpclasses.org\/blog\/post\/325-PHP-7-Nested-Anonymous-Classes-Tutorial.html","source":"phpclasses.org"},{"title":"The Beginners Guide to WooCommerce: Adding a New Order Part 3","url":"http:\/\/code.tutsplus.com\/articles\/the-beginners-guide-to-woocommerce-adding-a-new-order-part-3--cms-22692","source":"tutsplus.com"},{"title":"New in Symfony 2.8: Guard Authentication Component","url":"http:\/\/symfony.com\/blog\/new-in-symfony-2-8-guard-authentication-component","source":"symfony.com"},{"title":"10 Less-known (but awesome!) Laravel Collections Methods","url":"http:\/\/laraveldaily.com\/10-less-known-but-awesome-laravel-collections-methods\/","source":"laraveldaily.com"},{"title":"Running Symfony Applications with PHP-PM","url":"https:\/\/www.symfony.fi\/entry\/running-symfony-applications-with-php-pm","source":"symfony.fi"},{"title":"Find Easy Solutions with These Top CakePHP Based CMS","url":"http:\/\/www.cakephpexpert.com\/blog\/find-easy-solutions-with-these-top-cakephp-based-cms","source":"cakephpexpert.com"},{"title":"Why I\u2019m Joining YouTube Red","url":"http:\/\/www.johnmorrisonline.com\/why-im-joining-youtube-red\/","source":"johnmorrisonline.com"},{"title":"Benefits Of Setting-up Multi-Regional Stores With Magento Store Switcher","url":"http:\/\/www.fmeextensions.com\/blog\/benefits-of-setting-multi-regional-stores-by-using-magento-store-switcher\/?utm_source=rss&utm_medium=rss&utm_campaign=benefits-of-setting-multi-regional-stores-by-using-magento-store-switcher","source":"fmeextensions.com"},{"title":"Simple, Easy, Risk and Change","url":"http:\/\/blog.ircmaxell.com\/2015\/11\/simple-easy-risk-and-change.html","source":"ircmaxell.com"},{"title":"Dia de Muertos - Remembering PHP Community Members Who Have Died","url":"https:\/\/benramsey.com\/blog\/2015\/11\/dia-de-muertos\/","source":"benramsey.com"},{"title":"Tracking PHP API Accesses using Google Analytics Part 2: Recording API Accesses","url":"http:\/\/www.phpclasses.org\/blog\/package\/9414\/post\/2-Tracking-PHP-API-Accesses-using-Google-Analytics-Part-2-Recording-API-Accesses.html","source":"phpclasses.org"},{"title":"Building Database-free Websites with Statamic CMS","url":"http:\/\/www.sitepoint.com\/building-database-free-websites-with-statamic-cms\/","source":"sitepoint.com"}]