[{"title":"Coworker Coffee","url":"http:\/\/www.producthunt.com\/tech\/coworker-coffee","source":"producthunt.com"},{"title":"Quicklytics for Google Analytics","url":"http:\/\/www.producthunt.com\/tech\/quicklytics-for-google-analytics","source":"producthunt.com"},{"title":"Reddit in MS Outlook Skin","url":"http:\/\/www.producthunt.com\/tech\/reddit-in-ms-outlook-skin","source":"producthunt.com"},{"title":"BlackFriday.com","url":"http:\/\/www.producthunt.com\/tech\/blackfriday-com","source":"producthunt.com"},{"title":"Ola Money","url":"http:\/\/www.producthunt.com\/tech\/ola-money","source":"producthunt.com"},{"title":"Defocus","url":"http:\/\/www.producthunt.com\/tech\/defocus","source":"producthunt.com"},{"title":"Tutset","url":"http:\/\/www.producthunt.com\/tech\/tutset","source":"producthunt.com"},{"title":"LinkedIn ProFinder","url":"http:\/\/www.producthunt.com\/tech\/linkedin-profinder-2","source":"producthunt.com"},{"title":"K Blocker","url":"http:\/\/www.producthunt.com\/tech\/k-blocker","source":"producthunt.com"},{"title":"HangoverApp","url":"http:\/\/www.producthunt.com\/tech\/hangoverapp","source":"producthunt.com"},{"title":"Tweetpilot","url":"http:\/\/www.producthunt.com\/tech\/tweetpilot","source":"producthunt.com"},{"title":"Pikazo","url":"http:\/\/www.producthunt.com\/tech\/pikazo-2","source":"producthunt.com"},{"title":"remoteworks.io","url":"http:\/\/www.producthunt.com\/tech\/remoteworks-io","source":"producthunt.com"},{"title":"Briteverify","url":"http:\/\/www.producthunt.com\/tech\/briteverify-2","source":"producthunt.com"},{"title":"Zenefits Payroll","url":"http:\/\/www.producthunt.com\/tech\/zenefits-payroll","source":"producthunt.com"},{"title":"Product Valet","url":"http:\/\/www.producthunt.com\/tech\/product-valet","source":"producthunt.com"},{"title":"Super","url":"http:\/\/www.producthunt.com\/tech\/super-3","source":"producthunt.com"},{"title":"Flip","url":"http:\/\/www.producthunt.com\/tech\/flip-2","source":"producthunt.com"},{"title":"Yodel","url":"http:\/\/www.producthunt.com\/tech\/yodel","source":"producthunt.com"},{"title":"Notifier by ContentMarketer.io","url":"http:\/\/www.producthunt.com\/tech\/notifier-by-contentmarketer-io","source":"producthunt.com"},{"title":"Be Forever Me","url":"http:\/\/www.producthunt.com\/tech\/be-forever-me","source":"producthunt.com"},{"title":"Plant Link","url":"http:\/\/www.producthunt.com\/tech\/plant-link","source":"producthunt.com"},{"title":"Wisp","url":"http:\/\/www.producthunt.com\/tech\/wisp-2","source":"producthunt.com"},{"title":"Insight Timer 1.5","url":"http:\/\/www.producthunt.com\/tech\/insight-timer-1-5","source":"producthunt.com"},{"title":"Cannabox","url":"http:\/\/www.producthunt.com\/tech\/cannabox","source":"producthunt.com"},{"title":"Tipsy","url":"http:\/\/www.producthunt.com\/tech\/tipsy","source":"producthunt.com"},{"title":"ANKR","url":"http:\/\/www.producthunt.com\/tech\/ankr","source":"producthunt.com"},{"title":"Deploy PHP!","url":"http:\/\/www.producthunt.com\/tech\/deploy-php","source":"producthunt.com"},{"title":"Tumblr GIF Maker","url":"http:\/\/www.producthunt.com\/tech\/tumblr-gif-maker","source":"producthunt.com"},{"title":"Encore Music","url":"http:\/\/www.producthunt.com\/tech\/encore-music","source":"producthunt.com"},{"title":"Pool","url":"http:\/\/www.producthunt.com\/tech\/pool","source":"producthunt.com"},{"title":"Nostalgia Chest","url":"http:\/\/www.producthunt.com\/tech\/nostalgia-chest","source":"producthunt.com"},{"title":"Plag","url":"http:\/\/www.producthunt.com\/tech\/plag-4","source":"producthunt.com"},{"title":"Timbuk2 Sabbatical Travel Kit","url":"http:\/\/www.producthunt.com\/tech\/timbuk2-sabbatical-travel-kit","source":"producthunt.com"},{"title":"Momento 3","url":"http:\/\/www.producthunt.com\/tech\/momento-3","source":"producthunt.com"},{"title":"tl;dr Marketing","url":"http:\/\/www.producthunt.com\/tech\/tl-dr-marketing","source":"producthunt.com"},{"title":"Juvo","url":"http:\/\/www.producthunt.com\/tech\/juvo","source":"producthunt.com"},{"title":"#FaceParty","url":"http:\/\/www.producthunt.com\/tech\/faceparty","source":"producthunt.com"},{"title":"PriceLocal","url":"http:\/\/www.producthunt.com\/tech\/pricelocal","source":"producthunt.com"},{"title":"Direct Messenger","url":"http:\/\/www.producthunt.com\/tech\/direct-messenger","source":"producthunt.com"},{"title":"ParrotRead","url":"http:\/\/www.producthunt.com\/tech\/parrotread","source":"producthunt.com"},{"title":"Beagle Sense","url":"http:\/\/www.producthunt.com\/tech\/beagle-sense","source":"producthunt.com"},{"title":"Grsp","url":"http:\/\/www.producthunt.com\/tech\/grsp","source":"producthunt.com"},{"title":"24me Micro-Gifting","url":"http:\/\/www.producthunt.com\/tech\/24me-micro-gifting","source":"producthunt.com"},{"title":"Predict by Mixpanel","url":"http:\/\/www.producthunt.com\/tech\/predict-by-mixpanel","source":"producthunt.com"},{"title":"Figment VR","url":"http:\/\/www.producthunt.com\/tech\/figment-vr","source":"producthunt.com"},{"title":"Dressboom","url":"http:\/\/www.producthunt.com\/tech\/dressboom","source":"producthunt.com"},{"title":"Tripaya","url":"http:\/\/www.producthunt.com\/tech\/tripaya","source":"producthunt.com"},{"title":"Beautiful Earth","url":"http:\/\/www.producthunt.com\/tech\/beautiful-earth","source":"producthunt.com"},{"title":"Hello Hipmunk","url":"http:\/\/www.producthunt.com\/tech\/hello-hipmunk","source":"producthunt.com"},{"title":"Creative Class Contract","url":"http:\/\/www.producthunt.com\/tech\/creative-class-contract","source":"producthunt.com"},{"title":"Sigstr Signatures","url":"http:\/\/www.producthunt.com\/tech\/sigstr-signatures","source":"producthunt.com"},{"title":"Animaticons","url":"http:\/\/www.producthunt.com\/tech\/animaticons","source":"producthunt.com"},{"title":"Product Hunt + Baron Fig Notebook","url":"http:\/\/www.producthunt.com\/tech\/product-hunt-baron-fig-notebook","source":"producthunt.com"},{"title":"Kit","url":"http:\/\/www.producthunt.com\/tech\/kit-b299c7d9-9c94-4e5a-aed5-d60c36f24120","source":"producthunt.com"},{"title":"Google+","url":"http:\/\/www.producthunt.com\/tech\/google-6a5bb3df-7b29-45dc-9f2b-fde30bfe216c","source":"producthunt.com"},{"title":"Casper Sheets and Pillows","url":"http:\/\/www.producthunt.com\/tech\/casper-sheets-and-pillows","source":"producthunt.com"},{"title":"TeamGrid","url":"http:\/\/www.producthunt.com\/tech\/teamgrid","source":"producthunt.com"},{"title":"Kifi for Teams","url":"http:\/\/www.producthunt.com\/tech\/kifi-for-teams","source":"producthunt.com"},{"title":"PAVLOK","url":"http:\/\/www.producthunt.com\/tech\/pavlok-2","source":"producthunt.com"},{"title":"Hitch.ly","url":"http:\/\/www.producthunt.com\/tech\/hitch-ly","source":"producthunt.com"},{"title":"Brain.fm","url":"http:\/\/www.producthunt.com\/tech\/brain-fm","source":"producthunt.com"},{"title":"Mixmax Mail Merge","url":"http:\/\/www.producthunt.com\/tech\/mixmax-mail-merge","source":"producthunt.com"},{"title":"Mixology","url":"http:\/\/www.producthunt.com\/tech\/mixology","source":"producthunt.com"},{"title":"Dips","url":"http:\/\/www.producthunt.com\/tech\/dips-2","source":"producthunt.com"},{"title":"Terrorists to Cowards","url":"http:\/\/www.producthunt.com\/tech\/terrorists-to-cowards","source":"producthunt.com"},{"title":"Browserbite","url":"http:\/\/www.producthunt.com\/tech\/browserbite","source":"producthunt.com"},{"title":"Rally","url":"http:\/\/www.producthunt.com\/tech\/rally-4","source":"producthunt.com"},{"title":"Jumper","url":"http:\/\/www.producthunt.com\/tech\/jumper","source":"producthunt.com"},{"title":"ReallyColor","url":"http:\/\/www.producthunt.com\/tech\/reallycolor","source":"producthunt.com"},{"title":"Happy Cow","url":"http:\/\/www.producthunt.com\/tech\/happy-cow","source":"producthunt.com"},{"title":"PH.dog","url":"http:\/\/www.producthunt.com\/tech\/ph-dog","source":"producthunt.com"},{"title":"Unfiltered","url":"http:\/\/www.producthunt.com\/tech\/unfiltered","source":"producthunt.com"},{"title":"CardBoard","url":"http:\/\/www.producthunt.com\/tech\/cardboard","source":"producthunt.com"},{"title":"Tiki","url":"http:\/\/www.producthunt.com\/tech\/tiki","source":"producthunt.com"},{"title":"Keap","url":"http:\/\/www.producthunt.com\/tech\/keap","source":"producthunt.com"},{"title":"Writrsbloc","url":"http:\/\/www.producthunt.com\/tech\/writrsbloc-2","source":"producthunt.com"},{"title":"FreeSkies","url":"http:\/\/www.producthunt.com\/tech\/freeskies","source":"producthunt.com"},{"title":"Diehard Fan","url":"http:\/\/www.producthunt.com\/tech\/diehard-fan","source":"producthunt.com"},{"title":"Litographs Book Club","url":"http:\/\/www.producthunt.com\/tech\/litographs-book-club","source":"producthunt.com"},{"title":"Ajiri Tea and Ajiri Coffee","url":"http:\/\/www.producthunt.com\/tech\/ajiri-tea-and-ajiri-coffee","source":"producthunt.com"},{"title":"Koguma","url":"http:\/\/www.producthunt.com\/tech\/koguma","source":"producthunt.com"},{"title":"Johnny - the Apple Pencil case","url":"http:\/\/www.producthunt.com\/tech\/johnny-the-apple-pencil-case","source":"producthunt.com"}]