[{"title":"Programmers Design Differently: Why I Built a CSS Plugin for Sketch 3","url":"https:\/\/medium.com\/sketch-app-sources\/programmers-design-differently-why-i-built-a-css-plugin-for-sketch-3-52a1246305a4","source":"medium.com"},{"title":"Diamond grid layout with Sass","url":"http:\/\/www.chenhuijing.com\/blog\/diamond-grid-using-sass\/","source":"chenhuijing.com"},{"title":"Why future designers won\u2019t come from Art Schools","url":"https:\/\/medium.com\/@souheilmedaghri\/why-future-designers-won-t-come-from-art-schools-65e1c2c1c812","source":"medium.com"},{"title":"Why It\u2019s So Hard to Design Arabic Typefaces","url":"http:\/\/www.wired.com\/2015\/10\/why-its-so-hard-to-design-arabic-typefaces","source":"wired.com"},{"title":"Inspiration: Ginventory","url":"http:\/\/www.ginventory.co\/","source":"ginventory.co"},{"title":"Animated Gameboy in CSS","url":"http:\/\/snip.ly\/5Vpq","source":"snip.ly"}]