[{"title":"gliderlabs        \/        docker-alpine","url":"https:\/\/github.com\/gliderlabs\/docker-alpine","source":"github.com"},{"title":"vhf        \/        free-programming-books","url":"https:\/\/github.com\/vhf\/free-programming-books","source":"github.com"},{"title":"hsavit1        \/        Awesome-Swift-Education","url":"https:\/\/github.com\/hsavit1\/Awesome-Swift-Education","source":"github.com"},{"title":"onevcat        \/        Rainbow","url":"https:\/\/github.com\/onevcat\/Rainbow","source":"github.com"},{"title":"vuejs        \/        vue","url":"https:\/\/github.com\/vuejs\/vue","source":"github.com"},{"title":"sindresorhus        \/        awesome","url":"https:\/\/github.com\/sindresorhus\/awesome","source":"github.com"},{"title":"frogermcs        \/        LikeAnimation","url":"https:\/\/github.com\/frogermcs\/LikeAnimation","source":"github.com"},{"title":"jtleek        \/        datasharing","url":"https:\/\/github.com\/jtleek\/datasharing","source":"github.com"},{"title":"xinyu198736        \/        js2image","url":"https:\/\/github.com\/xinyu198736\/js2image","source":"github.com"},{"title":"Aufree        \/        ESTMusicPlayer","url":"https:\/\/github.com\/Aufree\/ESTMusicPlayer","source":"github.com"},{"title":"DanisFabric        \/        RainbowNavigation","url":"https:\/\/github.com\/DanisFabric\/RainbowNavigation","source":"github.com"},{"title":"dherman        \/        neon","url":"https:\/\/github.com\/dherman\/neon","source":"github.com"},{"title":"usablica        \/        intro.js","url":"https:\/\/github.com\/usablica\/intro.js","source":"github.com"},{"title":"l123456789jy        \/        Lazy","url":"https:\/\/github.com\/l123456789jy\/Lazy","source":"github.com"},{"title":"facebook        \/        react-native","url":"https:\/\/github.com\/facebook\/react-native","source":"github.com"},{"title":"FreeCodeCamp        \/        FreeCodeCamp","url":"https:\/\/github.com\/FreeCodeCamp\/FreeCodeCamp","source":"github.com"},{"title":"tldr-pages        \/        tldr","url":"https:\/\/github.com\/tldr-pages\/tldr","source":"github.com"},{"title":"hanks-zyh        \/        HTextView","url":"https:\/\/github.com\/hanks-zyh\/HTextView","source":"github.com"},{"title":"quantumfoam        \/        DVNA","url":"https:\/\/github.com\/quantumfoam\/DVNA","source":"github.com"},{"title":"renaudcerrato        \/        ToggleDrawable","url":"https:\/\/github.com\/renaudcerrato\/ToggleDrawable","source":"github.com"},{"title":"officert        \/        mongotron","url":"https:\/\/github.com\/officert\/mongotron","source":"github.com"},{"title":"djyde        \/        WebShell","url":"https:\/\/github.com\/djyde\/WebShell","source":"github.com"}]