[{"title":"How Heroku Platform API migrated to Active Record 4","url":"http:\/\/email.changelog.com\/t\/t-l-ikdkhtk-l-tt\/","source":"changelog.com"},{"title":"The Evolution of Swift [8:13]","url":"http:\/\/email.changelog.com\/t\/t-l-ikdkhtk-l-jy\/","source":"changelog.com"},{"title":"Securing your website with Let's Encrypt [8:36]","url":"http:\/\/email.changelog.com\/t\/t-l-ikdkhtk-l-jj\/","source":"changelog.com"},{"title":"How does Bundler work, anyway? [42:30]","url":"http:\/\/email.changelog.com\/t\/t-l-ikdkhtk-l-ji\/","source":"changelog.com"},{"title":"Node.js and Joyent [5:18]","url":"http:\/\/email.changelog.com\/t\/t-l-ikdkhtk-l-jd\/","source":"changelog.com"},{"title":"Ping The Changelog","url":"http:\/\/email.changelog.com\/t\/t-l-ikdkhtk-l-jh\/","source":"changelog.com"},{"title":"Italy on Rails","url":"http:\/\/email.changelog.com\/t\/t-l-ikdkhtk-l-ty\/","source":"changelog.com"},{"title":"HTTP-RPC","url":"http:\/\/email.changelog.com\/t\/t-l-ikdkhtk-l-tj\/","source":"changelog.com"},{"title":"Creating a Lightsaber with Polymer","url":"http:\/\/email.changelog.com\/t\/t-l-ikdkhtk-l-m\/","source":"changelog.com"},{"title":"Drill into Tasks and People on your Project","url":"http:\/\/email.changelog.com\/t\/t-l-ikdkhtk-l-c\/","source":"changelog.com"},{"title":"Move Fast and Fix Things","url":"http:\/\/email.changelog.com\/t\/t-l-ikdkhtk-l-q\/","source":"changelog.com"},{"title":"React Native Team AMA on Reddit","url":"http:\/\/email.changelog.com\/t\/t-l-ikdkhtk-l-a\/","source":"changelog.com"},{"title":"Backends for Frontends (BFF) at SoundCloud","url":"http:\/\/email.changelog.com\/t\/t-l-ikdkhtk-l-f\/","source":"changelog.com"},{"title":"Building a Rest API with the Bottle Framework","url":"http:\/\/email.changelog.com\/t\/t-l-ikdkhtk-l-z\/","source":"changelog.com"},{"title":"Ecto v1.1 released and Ecto v2.0 plans","url":"http:\/\/email.changelog.com\/t\/t-l-ikdkhtk-l-v\/","source":"changelog.com"},{"title":"Using React is a Business Decision, Not a Technology Choice","url":"http:\/\/email.changelog.com\/t\/t-l-ikdkhtk-l-e\/","source":"changelog.com"},{"title":"Battling BEM","url":"http:\/\/email.changelog.com\/t\/t-l-ikdkhtk-l-s\/","source":"changelog.com"},{"title":"Issue Stats","url":"http:\/\/email.changelog.com\/t\/t-l-ikdkhtk-l-g\/","source":"changelog.com"},{"title":"emacs-fireplace","url":"http:\/\/email.changelog.com\/t\/t-l-ikdkhtk-l-yd\/","source":"changelog.com"},{"title":"react-refetch","url":"http:\/\/email.changelog.com\/t\/t-l-ikdkhtk-l-yh\/","source":"changelog.com"},{"title":"Botkit","url":"http:\/\/email.changelog.com\/t\/t-l-ikdkhtk-l-yk\/","source":"changelog.com"},{"title":"git-appraise","url":"http:\/\/email.changelog.com\/t\/t-l-ikdkhtk-l-jl\/","source":"changelog.com"},{"title":"ursprung","url":"http:\/\/email.changelog.com\/t\/t-l-ikdkhtk-l-jr\/","source":"changelog.com"},{"title":"187: Redux, React, and Functional JavaScript with Dan Abramov","url":"http:\/\/email.changelog.com\/t\/t-l-ikdkhtk-l-j\/","source":"changelog.com"},{"title":"Must Watch Videos on Service Workers","url":"http:\/\/email.changelog.com\/t\/t-l-ikdkhtk-l-t\/","source":"changelog.com"},{"title":"curl to use HTTP\/2 by default","url":"http:\/\/email.changelog.com\/t\/t-l-ikdkhtk-l-d\/","source":"changelog.com"},{"title":"Open Sourcing Our Website","url":"http:\/\/email.changelog.com\/t\/t-l-ikdkhtk-l-h\/","source":"changelog.com"},{"title":"An Introduction to Web Applications with Docker","url":"http:\/\/email.changelog.com\/t\/t-l-ikdkhtk-l-u\/","source":"changelog.com"},{"title":"Regret Minimization Framework","url":"http:\/\/email.changelog.com\/t\/t-l-ikdkhtk-l-b\/","source":"changelog.com"},{"title":"My Positive Experience as a Woman in Tech","url":"http:\/\/email.changelog.com\/t\/t-l-ikdkhtk-l-n\/","source":"changelog.com"},{"title":"Benchmarking Streaming Computation Engines at Yahoo!","url":"http:\/\/email.changelog.com\/t\/t-l-ikdkhtk-l-p\/","source":"changelog.com"}]